refyn/__init__.py
refyn-0.0.1.dist-info/LICENSE
refyn-0.0.1.dist-info/METADATA
refyn-0.0.1.dist-info/WHEEL
refyn-0.0.1.dist-info/top_level.txt
refyn-0.0.1.dist-info/RECORD
